khufu/.DS_Store
khufu/__init__.py
khufu/__version__.py
khufu/cl_utils.py
khufu/config.codekit
khufu/default_settings.yaml
khufu/test_settings.yaml
khufu/utKit.py
khufu/addons/__init__.py
khufu/addons/closeIcon.py
khufu/addons/mediaObject.py
khufu/addons/popover.py
khufu/addons/well.py
khufu/buttons/__init__.py
khufu/buttons/button.py
khufu/buttons/buttonGroup.py
khufu/code/__init__.py
khufu/code/code.py
khufu/commonutils/__init__.py
khufu/commonutils/getpackagepath.py
khufu/dropdowns/__init__.py
khufu/dropdowns/dropdown.py
khufu/dropdowns/dropdownLinkList.py
khufu/forms/__init__.py
khufu/forms/checkbox.py
khufu/forms/controlRow.py
khufu/forms/form.py
khufu/forms/formActions.py
khufu/forms/formInput.py
khufu/forms/horizontalFormControlGroup.py
khufu/forms/horizontalFormControlLabel.py
khufu/forms/login_form.py
khufu/forms/radio.py
khufu/forms/searchForm.py
khufu/forms/select.py
khufu/forms/textarea.py
khufu/forms/uneditableInput.py
khufu/helpers/__init__.py
khufu/helpers/hide_from_device.py
khufu/helpers/unescape_html.py
khufu/images/__init__.py
khufu/images/image.py
khufu/images/imageWell.py
khufu/images/imagingModal.py
khufu/images/thumbnail_div.py
khufu/images/thumbnails.py
khufu/labelsAndBadges/__init__.py
khufu/labelsAndBadges/alert.py
khufu/labelsAndBadges/badge.py
khufu/labelsAndBadges/label.py
khufu/labelsAndBadges/progressBar.py
khufu/labelsAndBadges/stackedProgressBar.py
khufu/modals/__init__.py
khufu/modals/modal.py
khufu/modals/modalForm.py
khufu/navigation/__init__.py
khufu/navigation/is_navStyle_active.py
khufu/navigation/navBar.py
khufu/navigation/nav_list.py
khufu/navigation/pagination.py
khufu/navigation/responsive_navigation_bar.py
khufu/navigation/searchbox.py
khufu/navigation/tabbableNavigation.py
khufu/plots/__init__.py
khufu/plots/svg.py
khufu/scaffolding/__init__.py
khufu/scaffolding/_container.py
khufu/scaffolding/body.py
khufu/scaffolding/grid_column.py
khufu/scaffolding/grid_row.py
khufu/scaffolding/head.py
khufu/scaffolding/htmlDocument.py
khufu-1.3.3.dist-info/LICENSE
khufu-1.3.3.dist-info/METADATA
khufu-1.3.3.dist-info/WHEEL
khufu-1.3.3.dist-info/top_level.txt
khufu-1.3.3.dist-info/RECORD
