Metadata-Version: 2.1
Name: khufu
Version: 1.3.3
Summary: Twitter Bootstrap elements via Python
Home-page: https://github.com/thespacedoctor/khufu
Author: David Young
Author-email: davidrobertyoung@gmail.com
License: MIT
Download-URL: https://github.com/thespacedoctor/khufu/archive/v1.3.3.zip
Keywords: bootstrap, templating
Platform: UNKNOWN
Classifier: Development Status :: 4 - Beta
Classifier: License :: OSI Approved :: MIT License
Classifier: Programming Language :: Python :: 3.7
Classifier: Topic :: Utilities
License-File: LICENSE
Requires-Dist: pyyaml
Requires-Dist: khufu
Requires-Dist: fundamentals
Requires-Dist: numpy
